{
    "Questions":[
        {
            "Question": "This is an Alternate Question manually generated",
            "Explanation": "",
            "Image": "",
            "isToF":"",
            "ToFAnswer": "",
            "Answers":[
                {
                    "Text": "Mad Answer",
                    "Correct": "true"
                },
                {
                    "Text":"Not an Answer",
                    "Correct": "false"
                },
                {
                    "Text": "Beep Answer",
                    "Correct": "false"
                }
            ]
        }
    ]
}